userstorage/__init__.py
userstorage/__main__.py
userstorage/backend.py
userstorage/config.py
userstorage/errors.py
userstorage/file.py
userstorage/loop.py
userstorage/mount.py
userstorage/osutil.py
userstorage-0.5.3.dist-info/licenses/LICENSE
userstorage-0.5.3.dist-info/METADATA
userstorage-0.5.3.dist-info/WHEEL
userstorage-0.5.3.dist-info/entry_points.txt
userstorage-0.5.3.dist-info/top_level.txt
userstorage-0.5.3.dist-info/RECORD
