Metadata-Version: 2.4
Name: userstorage
Version: 0.5.3
Summary: Create storage for tests
Home-page: https://github.com/oVirt/userstorage
Author: oVirt Developers
Author-email: devel@ovirt.org
License: GPL-2.0-or-later
Classifier: Development Status :: 4 - Beta
Classifier: Environment :: Console
Classifier: Intended Audience :: Developers
Classifier: Operating System :: POSIX :: Linux
Classifier: Programming Language :: Python :: 3
Classifier: Topic :: Software Development :: Testing
License-File: LICENSE
Dynamic: author
Dynamic: author-email
Dynamic: classifier
Dynamic: description
Dynamic: description-content-type
Dynamic: home-page
Dynamic: license
Dynamic: license-file
Dynamic: summary
